{
  "$schema": "https://developer.microsoft.com/json-schemas/fabric/item/report/definition/visualContainer/2.6.0/schema.json",
  "name": "24b3d8f35e5a42ad887c",
  "position": {
    "x": 19.913569576490925,
    "y": 324.1486603284356,
    "z": 8000,
    "height": 69.697493517718229,
    "width": 77.441659464131376,
    "tabOrder": 8000
  },
  "visual": {
    "visualType": "image",
    "objects": {
      "image": [
        {
          "properties": {
            "sourceType": {
              "expr": {
                "Literal": {
                  "Value": "'imageUrl'"
                }
              }
            },
            "sourceUrl": {
              "expr": {
                "Literal": {
                  "Value": "'https://cdn-icons-png.flaticon.com/512/5932/5932658.png'"
                }
              }
            }
          }
        }
      ]
    },
    "visualContainerObjects": {
      "visualLink": [
        {
          "properties": {
            "show": {
              "expr": {
                "Literal": {
                  "Value": "true"
                }
              }
            },
            "tooltip": {
              "expr": {
                "Literal": {
                  "Value": "'Team Performance Trends'"
                }
              }
            },
            "type": {
              "expr": {
                "Literal": {
                  "Value": "'PageNavigation'"
                }
              }
            },
            "navigationSection": {
              "expr": {
                "Literal": {
                  "Value": "'cf68e24e12630e902050'"
                }
              }
            }
          }
        }
      ]
    },
    "drillFilterOtherVisuals": true
  }
}